gender_detection/README.md
gender_detection/__init__.py
gender_detection/_batch.py
gender_detection/_encoder.py
gender_detection/_version.py
gender_detection/api.py
gender_detection/classifier.py
gender_detection/constant.py
gender_detection/util.py
gender_detection/models/checkpoint
gender_detection/models/instance.pkl
gender_detection/models/model.ckpt.data-00000-of-00001
gender_detection/models/model.ckpt.index
gender_detection/models/model.ckpt.meta
gender_detection-0.2.2.dist-info/DESCRIPTION.rst
gender_detection-0.2.2.dist-info/METADATA
gender_detection-0.2.2.dist-info/RECORD
gender_detection-0.2.2.dist-info/WHEEL
gender_detection-0.2.2.dist-info/metadata.json
gender_detection-0.2.2.dist-info/top_level.txt
